admin_tools_google_analytics/__init__.py
admin_tools_google_analytics/googleapi.py
admin_tools_google_analytics/modules.py
admin_tools_google_analytics/template_loaders.py
admin_tools_google_analytics/static/admin_tools_google_analytics/css/Chart.min.css
admin_tools_google_analytics/static/admin_tools_google_analytics/js/chart.min.js
admin_tools_google_analytics/templates/admin/base.html
admin_tools_google_analytics/templates/admin_tools_google_analytics/module.html
admin_tools_google_analytics/templates/admin_tools_google_analytics/visitors_chart.html
admin_tools_google_analytics/templates/admin_tools_google_analytics/visitors_total.html
admin_tools_google_analytics-0.1.dist-info/LICENSE
admin_tools_google_analytics-0.1.dist-info/METADATA
admin_tools_google_analytics-0.1.dist-info/WHEEL
admin_tools_google_analytics-0.1.dist-info/top_level.txt
admin_tools_google_analytics-0.1.dist-info/RECORD
